ink/__init__.py
ink/cli.py
ink/commands.py
ink_notes-0.1.0.dist-info/licenses/LICENSE
ink_notes-0.1.0.dist-info/METADATA
ink_notes-0.1.0.dist-info/WHEEL
ink_notes-0.1.0.dist-info/entry_points.txt
ink_notes-0.1.0.dist-info/top_level.txt
ink_notes-0.1.0.dist-info/RECORD
