Metadata-Version: 2.4
Name: ink-notes
Version: 0.1.0
Summary: A simple and lightweight CLI tool for note taking.
Home-page: https://github.com/a0x0p/ink
Author: a0x0p
Author-email: 1travisxwalker5@gmail.com
License: MIT
License-File: LICENSE
Requires-Dist: click
Dynamic: author
Dynamic: author-email
Dynamic: home-page
Dynamic: license
Dynamic: license-file
Dynamic: requires-dist
Dynamic: summary
